bureaucracy/__init__.py
bureaucracy/replacements.py
bureaucracy/template.py
bureaucracy/utils.py
bureaucracy/powerpoint/__init__.py
bureaucracy/powerpoint/core.py
bureaucracy/powerpoint/engines.py
bureaucracy/powerpoint/exceptions.py
bureaucracy/powerpoint/placeholders.py
bureaucracy/powerpoint/shapes.py
bureaucracy/powerpoint/slides.py
bureaucracy/powerpoint/tables.py
burocracy-0.4.1.dist-info/DESCRIPTION.rst
burocracy-0.4.1.dist-info/METADATA
burocracy-0.4.1.dist-info/RECORD
burocracy-0.4.1.dist-info/WHEEL
burocracy-0.4.1.dist-info/metadata.json
burocracy-0.4.1.dist-info/top_level.txt
tests/powerpoint/__init__.py
tests/powerpoint/test_containers.py
tests/powerpoint/test_templates.py
