Metadata-Version: 2.0
Name: burocracy
Version: 0.4.1
Summary: Templating and pdf generation for docx/pptx files
Home-page: UNKNOWN
Author: Maykin Media, Robin Ramael, Sergei Maertens
Author-email: robin.ramael@maykinmedia.nl, sergei@maykinmedia.nl
License: MIT
Platform: UNKNOWN
Classifier: Development Status :: 3 - Alpha
Classifier: Environment :: Web Environment
Classifier: Intended Audience :: Developers
Classifier: Operating System :: OS Independent
Classifier: Programming Language :: Python
Classifier: Programming Language :: Python :: 3
Classifier: Programming Language :: Python :: 3.4
Classifier: Programming Language :: Python :: 3.5
Classifier: Topic :: Internet :: WWW/HTTP
Classifier: Topic :: Internet :: WWW/HTTP :: Dynamic Content
Requires-Dist: pypandoc
Requires-Dist: python-docx
Requires-Dist: python-pptx (>=0.6.2)
